YuanmengXiangmuBijiWangzhuanJuejinShicaoXiangmuDianzishu20200229/README.md
YuanmengXiangmuBijiWangzhuanJuejinShicaoXiangmuDianzishu20200229/__init__.py
YuanmengXiangmuBijiWangzhuanJuejinShicaoXiangmuDianzishu20200229/__main__.py
YuanmengXiangmuBijiWangzhuanJuejinShicaoXiangmuDianzishu20200229/file.pdf
YuanmengXiangmuBijiWangzhuanJuejinShicaoXiangmuDianzishu20200229/index.html
yuanmeng_xiangmu_biji_wangzhuan_juejin_shicao_xiangmu_dianzishu_20200229-2024.3.6.0.dist-info/METADATA
yuanmeng_xiangmu_biji_wangzhuan_juejin_shicao_xiangmu_dianzishu_20200229-2024.3.6.0.dist-info/WHEEL
yuanmeng_xiangmu_biji_wangzhuan_juejin_shicao_xiangmu_dianzishu_20200229-2024.3.6.0.dist-info/entry_points.txt
yuanmeng_xiangmu_biji_wangzhuan_juejin_shicao_xiangmu_dianzishu_20200229-2024.3.6.0.dist-info/top_level.txt
yuanmeng_xiangmu_biji_wangzhuan_juejin_shicao_xiangmu_dianzishu_20200229-2024.3.6.0.dist-info/RECORD
